mpmath/__init__.py
mpmath/__main__.py
mpmath/_interactive.py
mpmath/ctx_base.py
mpmath/ctx_fp.py
mpmath/ctx_iv.py
mpmath/ctx_mp.py
mpmath/ctx_mp_python.py
mpmath/function_docs.py
mpmath/identification.py
mpmath/libfp.py
mpmath/math2.py
mpmath/rational.py
mpmath/usertools.py
mpmath/visualization.py
mpmath/calculus/__init__.py
mpmath/calculus/approximation.py
mpmath/calculus/calculus.py
mpmath/calculus/differentiation.py
mpmath/calculus/extrapolation.py
mpmath/calculus/inverselaplace.py
mpmath/calculus/odes.py
mpmath/calculus/optimization.py
mpmath/calculus/polynomials.py
mpmath/calculus/quadrature.py
mpmath/functions/__init__.py
mpmath/functions/bessel.py
mpmath/functions/elliptic.py
mpmath/functions/expintegrals.py
mpmath/functions/factorials.py
mpmath/functions/functions.py
mpmath/functions/hypergeometric.py
mpmath/functions/orthogonal.py
mpmath/functions/qfunctions.py
mpmath/functions/rszeta.py
mpmath/functions/signals.py
mpmath/functions/theta.py
mpmath/functions/zeta.py
mpmath/functions/zetazeros.py
mpmath/libmp/__init__.py
mpmath/libmp/backend.py
mpmath/libmp/gammazeta.py
mpmath/libmp/libelefun.py
mpmath/libmp/libhyper.py
mpmath/libmp/libintmath.py
mpmath/libmp/libmpc.py
mpmath/libmp/libmpf.py
mpmath/libmp/libmpi.py
mpmath/matrices/__init__.py
mpmath/matrices/calculus.py
mpmath/matrices/eigen.py
mpmath/matrices/eigen_symmetric.py
mpmath/matrices/linalg.py
mpmath/matrices/matrices.py
mpmath/tests/test_basic_ops.py
mpmath/tests/test_bitwise.py
mpmath/tests/test_calculus.py
mpmath/tests/test_cli.py
mpmath/tests/test_compatibility.py
mpmath/tests/test_convert.py
mpmath/tests/test_diff.py
mpmath/tests/test_division.py
mpmath/tests/test_eigen.py
mpmath/tests/test_eigen_symmetric.py
mpmath/tests/test_elliptic.py
mpmath/tests/test_extra_gamma.py
mpmath/tests/test_extra_zeta.py
mpmath/tests/test_format.py
mpmath/tests/test_fp.py
mpmath/tests/test_functions.py
mpmath/tests/test_functions2.py
mpmath/tests/test_gammazeta.py
mpmath/tests/test_hp.py
mpmath-1.4.0a8.dist-info/licenses/LICENSE
mpmath-1.4.0a8.dist-info/METADATA
mpmath-1.4.0a8.dist-info/WHEEL
mpmath-1.4.0a8.dist-info/top_level.txt
mpmath-1.4.0a8.dist-info/zip-safe
mpmath-1.4.0a8.dist-info/RECORD
