Metadata-Version: 2.4
Name: mpmath
Version: 1.4.0a8
Summary: Python library for arbitrary-precision floating-point arithmetic
Author-email: Fredrik Johansson <fredrik.johansson@gmail.com>
License-Expression: BSD-3-Clause
Project-URL: Homepage, https://mpmath.org/
Project-URL: Source Code, https://github.com/mpmath/mpmath
Project-URL: Bug Tracker, https://github.com/mpmath/mpmath/issues
Project-URL: Documentation, http://mpmath.org/doc/current/
Classifier: Topic :: Scientific/Engineering :: Mathematics
Classifier: Topic :: Software Development :: Libraries :: Python Modules
Classifier: Programming Language :: Python
Classifier: Programming Language :: Python :: 3
Classifier: Programming Language :: Python :: 3 :: Only
Classifier: Programming Language :: Python :: 3.9
Classifier: Programming Language :: Python :: 3.10
Classifier: Programming Language :: Python :: 3.11
Classifier: Programming Language :: Python :: 3.12
Classifier: Programming Language :: Python :: 3.13
Classifier: Programming Language :: Python :: 3.14
Classifier: Programming Language :: Python :: Free Threading :: 2 - Beta
Classifier: Programming Language :: Python :: Implementation :: CPython
Classifier: Programming Language :: Python :: Implementation :: PyPy
Requires-Python: >=3.9
License-File: LICENSE
Provides-Extra: tests
Requires-Dist: pytest>=6; extra == "tests"
Requires-Dist: numpy; python_version < "3.14" and extra == "tests"
Requires-Dist: packaging; extra == "tests"
Requires-Dist: pytest-timeout; extra == "tests"
Requires-Dist: matplotlib; (platform_python_implementation != "PyPy" and python_version < "3.14") and extra == "tests"
Requires-Dist: pexpect; extra == "tests"
Requires-Dist: ipython; extra == "tests"
Requires-Dist: hypothesis; extra == "tests"
Provides-Extra: develop
Requires-Dist: mpmath[tests]; extra == "develop"
Requires-Dist: flake518>=1.5; extra == "develop"
Requires-Dist: pytest-cov; extra == "develop"
Requires-Dist: wheel; extra == "develop"
Requires-Dist: build; extra == "develop"
Provides-Extra: gmpy2
Requires-Dist: gmpy2>=2.3.0a1; platform_python_implementation != "PyPy" and extra == "gmpy2"
Provides-Extra: gmpy
Requires-Dist: mpmath[gmpy2]; extra == "gmpy"
Provides-Extra: gmp
Requires-Dist: python-gmp>=0.4; platform_python_implementation != "PyPy" and extra == "gmp"
Provides-Extra: docs
Requires-Dist: sphinx; extra == "docs"
Requires-Dist: matplotlib; (platform_python_implementation != "PyPy" and python_version < "3.14") and extra == "docs"
Requires-Dist: sphinxcontrib-autoprogram; extra == "docs"
Provides-Extra: ci
Requires-Dist: pytest-xdist; extra == "ci"
Requires-Dist: diff_cover; extra == "ci"
Dynamic: license-file
